[
  {
    "slug": "account/billing",
    "title": "Billing",
    "content": "# Fatturazione\n\nScegli un piano, gestisci il tuo abbonamento e scopri cosa ottieni con Pro.\n\n## Gratuito vs Pro\n\nLanguage Player è gratuito, con un aggiornamento opzionale a Pro che sblocca l'esperienza completa.\n\n| Funzionalità | Gratuito | Pro |\n|---|---|---|\n| Oltre 600.000 video in più di 207 lingue | ✅ | ✅ |\n| Dizionario con collocazioni, esempi e coniugazioni verbali | ✅ | ✅ |\n| Scomposizione dei caratteri cinesi | ✅ | ✅ |\n| Trascrizioni interattive con traduzione | Prime 10 righe | Trascrizione completa |\n| Esempi di parole nei video | 2 per parola | Centinaia per parola |\n| Spiegazioni delle parole con AI | — | ✅ |\n| Supporto prioritario | — | ✅ |\n\n## Piani\n\n| Piano | Prezzo | Fatturazione |\n|---|---|---|\n| **Mensile** | US$10/mese | Fatturato mensilmente. Annulla quando vuoi. |\n| **Annuale** | US$90/anno | Fatturato annualmente. Risparmia il 25% rispetto al mensile. |\n| **A vita** | US$169 | Non scade mai. Paga una volta, accesso per sempre. |\n\nTutti i piani includono una Garanzia di rimborso di 14 giorni. Domande?\n\n## Come Aggiornare\n\n1. Apri il tuo **[Profilo](/docs/account/profile)** dal menu in alto a destra\n2. Scorri fino alla sezione **Abbonamento**\n3. Clicca su **Aggiorna a Pro** (o **Aggiorna** se sei già su un piano Pro)\n4. Scegli un piano — Mensile, Annuale o A vita\n5. Seleziona un metodo di pagamento e completa l'acquisto\n\nDopo il pagamento, verrai reindirizzato a una pagina di conferma. Le tue funzionalità Pro sono attive immediatamente — non è necessario disconnettersi o aggiornare la pagina.\n\n## Metodi di Pagamento\n\n| Metodo | Disponibile per | Valuta |\n|---|---|---|\n| Carta di Credito | Tutti i piani | USD |\n| WeChat Pay | Tutti i piani | CNY |\n| Alipay | Tutti i piani | CNY |\n| PayPal è disponibile anche per acquisti a vita. | Solo a vita | USD |\n\nI pagamenti con carta di credito sono elaborati in modo sicuro tramite Stripe. I dettagli della tua carta non vengono mai memorizzati sui nostri server.\n\n## Gestione dell'Abbonamento\n\n### Controlla il Tuo Stato\n\nIl tuo piano attuale, il ciclo di fatturazione e la data di rinnovo sono mostrati nella pagina del tuo **[Profilo](/docs/account/profile)** nella sezione Abbonamento.\n\n### Annulla il Rinnovo Automatico\n\nI piani Mensile e Annuale si rinnovano automaticamente. Per interrompere il rinnovo automatico:\n\n1. Vai al tuo **[Profilo](/docs/account/profile)**\n2. Nella sezione Abbonamento, clicca su **Annulla rinnovo automatico**\n3. Conferma cliccando su **Conferma cancellazione**\n\nIl tuo accesso Pro continua fino alla fine del periodo di fatturazione corrente. Successivamente, il tuo account tornerà alla versione Gratuita e conserverai tutte le parole salvate, la cronologia di visione e le impostazioni.\n\n### Rinnova un Abbonamento Scaduto\n\nSe il tuo abbonamento Pro è scaduto, clicca su **Rinnova** nella pagina del tuo profilo per abbonarti di nuovo. Tutti i tuoi dati vengono preservati — non si perde nulla quando un abbonamento scade.\n\n### Aggiorna il Tuo Piano\n\nPuoi passare dal piano Mensile a quello Annuale o A vita in qualsiasi momento:\n\n1. Vai al tuo **[Profilo](/docs/account/profile)**\n2. Clicca su **Aggiorna** nella sezione Abbonamento\n3. Scegli il tuo nuovo piano e completa il pagamento\n\nQuando effettui l'aggiornamento, il valore residuo del tuo piano attuale viene accreditato sul nuovo. Il tuo nuovo ciclo di fatturazione inizia immediatamente.\n\n## Suggerimenti\n\n- La pagina Passa a Pro mostra i prezzi in tempo reale — nessuna commissione nascosta o tasse aggiunte al momento del pagamento\n- Il piano A vita è un pagamento unico senza costi ricorrenti — 1. Supponendo che vivrai più di 2,4 anni.\n- Annullare il rinnovo automatico non elimina nulla — mantieni l'accesso Pro completo fino alla fine del periodo\n- Se incontri problemi di pagamento, contatta [Supporto email](mailto:jon.long@zerotohero.ca) e ti aiuteremo entro 24 ore"
  },
  {
    "slug": "media/explore",
    "title": "Esplora",
    "content": "# Esplora\n\nScopri video nella tua lingua di destinazione, adatti al tuo livello.\n\n## Come funziona\n\nLa pagina Esplora mostra video consigliati per la tua coppia linguistica. Ogni video proviene da YouTube ed è selezionato per l'apprendimento linguistico — escludiamo contenuti musicali e di intrattenimento (hanno una loro [Musica e Intrattenimento](/docs/media/music) dedicata).\n\nI video sono ordinati per popolarità e filtrati per difficoltà quando selezioni un livello. Il motore di raccomandazione impara dalla tua cronologia di visione, quindi i video che hai già visto non appariranno più.\n\n## Filtro per livello\n\nLe etichette in alto ti permettono di filtrare per livello di competenza. Le etichette si adattano alla tua lingua di destinazione:\n\n| L2 | Etichette mostrate |\n|---|---|\n| Cinese | HSK 1 → HSK 7-9 |\n| Giapponese | JLPT Pre-N5 → N1 |\n| Coreano | TOPIK Pre-1 → 6 |\n| Inglese | IELTS 1 → 9 |\n| Altre | CEFR Pre-A1 → C2 |\n\nClicca un'etichetta per filtrare i video a quel livello. Clicca **Tutti** per vedere video di ogni livello. Il filtro ricorda la tua scelta mentre navighi e si resetta al tuo livello di competenza salvato quando torni.\n\n## Schede video\n\nOgni scheda mostra un **indicatore di livello** colorato nell'angolo in alto a sinistra. Vedi [Come viene calcolata la difficoltà](#come-viene-calcolata-la-difficoltà) per sapere come vengono determinati questi livelli.\n\nClicca qualsiasi scheda per aprire il lettore video. Quando torni a Esplora, la tua posizione nell'elenco viene preservata esattamente dove l'avevi lasciata.\n\n### Azioni del canale\n\nOgni scheda video ha un menu **…** nell'angolo in alto a destra con due opzioni:\n\n- **Abbònati** — I video di questo canale appariranno per primi nei tuoi consigli. Circa il 25% di ogni pagina è riservato ai canali a cui sei iscritto, così vedrai sempre i loro contenuti più recenti in cima. Utile per canali che vuoi seguire regolarmente — testate giornalistiche, creatori educativi o i tuoi vlogger preferiti.\n\n- **Non interessato** — I video di questo canale saranno nascosti completamente dai tuoi consigli. Utile per canali che appaiono spesso ma non sono adatti — magari il contenuto è troppo avanzato, troppo facile, o semplicemente non pertinente ai tuoi obiettivi di apprendimento.\n\nLe tue preferenze sui canali sono salvate per lingua, quindi iscriverti a un canale di notizie in Giapponese non influenzerà i tuoi consigli in Coreano. Puoi gestire tutti i tuoi abbonamenti e canali nascosti dal tuo profilo.\n\n## Come viene calcolata la difficoltà\n\nA ogni video viene assegnato un punteggio di difficoltà basato sulla frequenza delle parole nei suoi sottotitoli. Il sistema utilizza liste di frequenza Zipf per lingua — grandi tabelle che classificano quanto ogni parola è comune nei testi reali. Una parola come \"il\" ha una frequenza alta (comune), mentre \"anticonformista\" ha una frequenza bassa (rara).\n\nI punteggi sono raggruppati in 7 livelli usando soglie esponenziali: le prime 1/127 parole più frequenti sono livello 1, le successive 2/127 sono livello 2, le successive 4/127 sono livello 3, e così via — raddoppiando ogni passo. Il livello 7 copre le 64/127 parole più rare.\n\nPoiché le distribuzioni di frequenza delle parole differiscono tra le lingue, le soglie sono **specifiche per lingua**. Un punteggio di difficoltà di 0.008 in Giapponese corrisponde a JLPT N1 (livello 6), mentre lo stesso punteggio in Coreano corrisponde a TOPIK 3 (livello 4). Il frontend recupera queste soglie una volta dal backend e le usa per etichettare ogni scheda video.\n\nLe tue preferenze sui canali sono salvate per lingua, quindi iscriverti a un canale di notizie in Giapponese non influenzerà i tuoi consigli in Coreano. Puoi gestire tutti i tuoi abbonamenti e canali nascosti dal tuo profilo.\n\n## Suggerimenti\n\n- Imposta il tuo livello di competenza nella tua [pagina profilo](/docs/account/profile) così Esplora inizia con il filtro giusto\n- Cambia livello per trovare contenuti più facili o più difficili — tornare indietro è istantaneo\n- Usa [Musica e Intrattenimento](/docs/media/music) per video musicali e contenuti di intrattenimento\n- La tua cronologia di visione è privata e viene usata solo per evitare di mostrare lo stesso video due volte"
  },
  {
    "slug": "reading/epub",
    "title": "Lettore EPUB",
    "content": "# Lettore EPUB\n\nRead EPUB e-books with interactive word lookup, per-block translation, and progress that persists across sessions.\n\n## Getting Started\n\n### Upload an EPUB\n\n1. Navigate to **Reading → Lettore EPUB** in the menu\n2. **Drag & drop** an `.epub` file onto the upload zone, or click **Browse** to select one from your device\n3. The cover image appears — tap it to start reading\n\nThe file is stored locally in your browser (IndexedDB). Next time you visit, it will load automatically and you'll resume from where you left off.\n\n### Navigation\n\n| Feature | How |\n|---|---|\n| **Next/Previous chapter** | Use the buttons at the top of the sidebar, or click chapter titles in the table of contents |\n| **Collapse/expand sidebar** | Click the `≡` toggle in the top-right corner of the title bar |\n| **Close the book** | Click `✕ Close` in the title bar to return to the upload screen |\n| **Page turn within a chapter** | Use `←` / `→` keys or the page controls at the bottom of the reader |\n| **Table of contents** | Nested TOC items are indented for easy navigation |\n\n### Reading Features\n\n- **Click any word** to look up its dictionary definition, pronunciation, and example sentences\n- **Per-block translation** — Click the `Languages` icon in the page nav bar to translate the current page's visible blocks\n- **Auto-translate on page turn** — When translation is enabled, the next page's content is translated automatically\n- **Inline translation display** — On wide screens, original and translation appear side by side. On narrow screens, translation appears below each block.\n\n## Supported Formats\n\n- **`.epub`** — Standard EPUB files (EPUB 2 and EPUB 3)\n- **`.epub` with furigana/ruby** — Giapponese books with ruby annotations are stripped of furigana, keeping only the base kanji text\n- **Vertical text** — Books with CSS `writing-mode: vertical-rl` are detected (display uses standard horizontal layout for readability)\n\n## Progress Saving\n\nYour reading position is saved automatically in your browser:\n\n- **Current chapter** is saved when you switch chapters\n- **Text anchor** (the first ~40 characters of the visible page) is saved when you turn pages\n- On your next visit, the book reloads and scrolls to the correct position\n\n**Note:** Progress is stored locally (IndexedDB), not synced to the cloud. Only one book is stored at a time — uploading a new one replaces the previous.\n\n## Getting Free EPUBs\n\n- **[Project Gutenberg](https://www.gutenberg.org/)** — 70,000+ free ebooks in many languages (look for \" EPUB with images\" or \" Plain Text UTF-8\")\n- **[Aozora Bunko](https://www.aozora.gr.jp/)** (青空文庫) — Giapponese literature, public domain\n- **[Wikisource](https://wikisource.org/)** — Public domain texts in many languages, downloadable as EPUB\n"
  },
  {
    "slug": "vocab/review",
    "title": "Ripasso",
    "content": "# Ripasso\n\nRipasso your saved vocabulary with spaced repetition flashcards.\n\n## How It Works\n\nEach saved word becomes a flashcard. The front shows the sentence where you saved the word — the word itself is highlighted so you can spot it instantly. Your job is to recall the meaning from context.\n\nTap the card (or press Space) to reveal the back. You'll see the full dictionary entry with definitions, examples, inflections, and an AI explanation. Compare what you recalled with the actual definition, then rate yourself.\n\nThe next time you see the word depends on your rating. Words you know well appear less often. Words you struggle with come back sooner. This is called spaced repetition — it's the same technique used by Anki.\n\n## Rating a Card\n\nAfter revealing the back, rate how well you remembered:\n\n| Button | Key | When to use |\n|---|---|---|\n| Again | 1 | You forgot entirely |\n| Hard | 2 | You recalled with difficulty |\n| Good | 3 | You recalled correctly |\n| Easy | 4 | You recalled instantly |\n\nYou can also tap the **left half** of the card for Again, or the **right half** for Good. A colored toast confirms your choice.\n\n## Card Counts\n\nThe top of the screen shows three colored indicators:\n\n- **Blue** — New cards you're seeing for the first time today\n- **Red** — Cards you're relearning after forgetting\n- **Green** — Cards coming back for a scheduled review\n\nThe daily limit for new cards is 20 by default. You can change it in [Impostazioni](/docs/general/settings).\n\n## Context & Translation\n\nEvery card shows the sentence where you saved the word. The exact word form is highlighted. Below it you'll see where the word came from (the video title or text name, plus the date).\n\nIf you have \"Mostra traduzione\" enabled in Impostazioni, the card shows the Inglese translation of the sentence when you reveal the back. If no saved translation exists, it fetches one automatically.\n\nThe context sentence has a hover menu (the three dots) for copying the text, speaking it aloud, getting an AI explanation, or translating it on the spot.\n\n## Removing a Word\n\nTo remove a word from your review deck, unsave it from the dictionary entry on the back of the card. The next card slides into place automatically.\n\n## Keyboard Shortcuts\n\n- **Space** or **Enter** — Reveal the back, or rate Good (when back is shown)\n- **1–4** — Rate Again, Hard, Good, Easy (when back is shown)\n\n## Tips\n\n- Ripasso daily. Even 5 minutes makes a difference.\n- Be strict with Again. If you couldn't recall it in real life, it counts as a fail.\n- Use the context sentence. Seeing the word in its original sentence is more effective than memorizing in isolation.\n- Tap the three dots on the context sentence to translate or explain the full line before rating.\n- Adjust your daily new card limit in Impostazioni if 20 feels too many or too few.\n"
  }
]